lmms_lean_runner-0.0.1.dist-info/licenses/LICENSE
packages/client/test_file_support.py
packages/client/lean_runner/__init__.py
packages/client/lean_runner/client/__init__.py
packages/client/lean_runner/client/client.py
packages/client/lean_runner/client/aio/__init__.py
packages/client/lean_runner/client/aio/client.py
packages/client/lean_runner/proof/__init__.py
packages/client/lean_runner/proof/proto.py
packages/server/lean_server/__init__.py
packages/server/lean_server/app/__init__.py
packages/server/lean_server/app/args.py
packages/server/lean_server/app/db.py
packages/server/lean_server/app/lifespan.py
packages/server/lean_server/app/prove.py
packages/server/lean_server/app/serve.py
packages/server/lean_server/app/utils.py
packages/server/lean_server/config/__init__.py
packages/server/lean_server/config/config.py
packages/server/lean_server/database/__init__.py
packages/server/lean_server/database/proof.py
packages/server/lean_server/manager/__init__.py
packages/server/lean_server/manager/proof_manager.py
packages/server/lean_server/proof/__init__.py
packages/server/lean_server/proof/lean.py
packages/server/lean_server/proof/proto.py
packages/server/lean_server/utils/uuid/uuid.py
lmms_lean_runner-0.0.1.dist-info/METADATA
lmms_lean_runner-0.0.1.dist-info/WHEEL
lmms_lean_runner-0.0.1.dist-info/top_level.txt
lmms_lean_runner-0.0.1.dist-info/RECORD
